ezfileutils/__init__.py
ezfileutils/ezfileutils.py
ezfileutils-1.0.54.dist-info/METADATA
ezfileutils-1.0.54.dist-info/WHEEL
ezfileutils-1.0.54.dist-info/entry_points.txt
ezfileutils-1.0.54.dist-info/top_level.txt
ezfileutils-1.0.54.dist-info/RECORD
