Metadata-Version: 2.1
Name: ezfileutils
Version: 1.0.54
Summary: A Python utility script for common file operations.
Author: Dom
Author-email: tanagitanagiakori@gmail.com
